disk_analyzer/__init__.py
disk_analyzer/__main__.py
disk_analyzer/analyzer.py
disk_analyzer/cli.py
disk_analyzer/web_app.py
disk_space_analyzer-0.1.0.dist-info/licenses/LICENSE
disk_space_analyzer-0.1.0.dist-info/METADATA
disk_space_analyzer-0.1.0.dist-info/WHEEL
disk_space_analyzer-0.1.0.dist-info/entry_points.txt
disk_space_analyzer-0.1.0.dist-info/top_level.txt
disk_space_analyzer-0.1.0.dist-info/RECORD
