Metadata-Version: 2.4
Name: disk-space-analyzer
Version: 0.1.0
Summary: 一个功能强大的磁盘空间分析和管理工具，提供直观的可视化界面、安全的删除机制和灵活的分析选项
Home-page: https://github.com/username/disk_analyzer
Author: Disk Analyzer Team
License: MIT
Project-URL: Homepage, https://github.com/username/disk_analyzer
Project-URL: Documentation, https://github.com/username/disk_analyzer#readme
Project-URL: Repository, https://github.com/username/disk_analyzer.git
Project-URL: Issues, https://github.com/username/disk_analyzer/issues
Keywords: disk,analyzer,space,filesystem,web,visualization
Classifier: Development Status :: 3 - Alpha
Classifier: Intended Audience :: System Administrators
Classifier: Intended Audience :: End Users/Desktop
Classifier: Topic :: System :: Filesystems
Classifier: Topic :: System :: Systems Administration
Classifier: Topic :: Utilities
Classifier: License :: OSI Approved :: MIT License
Classifier: Programming Language :: Python :: 3
Classifier: Programming Language :: Python :: 3.8
Classifier: Programming Language :: Python :: 3.9
Classifier: Programming Language :: Python :: 3.10
Classifier: Programming Language :: Python :: 3.11
Classifier: Programming Language :: Python :: 3.12
Classifier: Operating System :: POSIX :: Linux
Classifier: Operating System :: MacOS
Classifier: Operating System :: Microsoft :: Windows
Requires-Python: >=3.8
License-File: LICENSE
Requires-Dist: flask>=2.3.0
Requires-Dist: flask-cors>=4.0.0
Provides-Extra: dev
Requires-Dist: pytest>=7.0.0; extra == "dev"
Requires-Dist: pytest-cov>=4.0.0; extra == "dev"
Requires-Dist: black>=23.0.0; extra == "dev"
Requires-Dist: flake8>=6.0.0; extra == "dev"
Dynamic: home-page
Dynamic: license-file
Dynamic: requires-python
